MeatInject-1.0.2.dist-info/DESCRIPTION.rst
MeatInject-1.0.2.dist-info/METADATA
MeatInject-1.0.2.dist-info/RECORD
MeatInject-1.0.2.dist-info/WHEEL
MeatInject-1.0.2.dist-info/entry_points.txt
MeatInject-1.0.2.dist-info/metadata.json
MeatInject-1.0.2.dist-info/top_level.txt
meatinject/__init__.py
meatinject/meatinject.py
